flask_zs/__init__.py
flask_zs/bin/__init__.py
flask_zs/bin/collect_models.py
flask_zs/errorhandler.py
flask_zs/exceptions.py
flask_zs/helpers.py
flask_zs/response.py
flask_zs-1.0.8.dist-info/LICENSE
flask_zs-1.0.8.dist-info/METADATA
flask_zs-1.0.8.dist-info/WHEEL
flask_zs-1.0.8.dist-info/entry_points.txt
flask_zs-1.0.8.dist-info/RECORD
