Metadata-Version: 2.1
Name: flask-zs
Version: 1.0.8
Summary: A helpers for Flask.
Home-page: https://github.com/codeif/flask-zs
License: MIT
Author: codeif
Author-email: me@codeif.com
Requires-Python: >=3.8,<4.0
Classifier: License :: OSI Approved :: MIT License
Classifier: Programming Language :: Python :: 3
Classifier: Programming Language :: Python :: 3.8
Classifier: Programming Language :: Python :: 3.9
Classifier: Programming Language :: Python :: 3.10
Classifier: Programming Language :: Python :: 3.11
Provides-Extra: full
Provides-Extra: http-client
Provides-Extra: mixins
Requires-Dist: Flask
Requires-Dist: flask-http-client ; extra == "http-client" or extra == "full"
Requires-Dist: requests
Requires-Dist: zs-mixins ; extra == "mixins" or extra == "full"
Project-URL: Repository, https://github.com/codeif/flask-zs
